<?xml version="1.0" encoding="UTF-8"?>
<!DOCTYPE suite SYSTEM "https://testng.org/testng-1.0.dtd">
<suite name="Suite">
<listeners>
		<listener class-name="listeners.ExtentTestListener" />
	</listeners>
  <test thread-count="5" name="Test">
    <classes>
      <class name="tests.SchemaTest"/>
      <class name="tests.DeleteUserTest"/>
      <class name="tests.UpdateTest"/>
      <class name="tests.UserTests"/>
      <class name="tests.ListOfUsers"/>
      <class name="tests.FailTests"/>
    </classes>
  </test> <!-- Test -->
</suite> <!-- Suite -->
